riotee_probe/__init__.py
riotee_probe/cli.py
riotee_probe/intelhex.py
riotee_probe/probe.py
riotee_probe/protocol.py
riotee_probe/session.py
riotee_probe/target.py
riotee_probe-1.1.0.dist-info/entry_points.txt
riotee_probe-1.1.0.dist-info/LICENSE.txt
riotee_probe-1.1.0.dist-info/WHEEL
riotee_probe-1.1.0.dist-info/METADATA
riotee_probe-1.1.0.dist-info/RECORD
